README
setup.py
hgrecipe/__init__.py
hgrecipe/recipe.py
hgrecipe/tests.py
hgrecipe.egg-info/PKG-INFO
hgrecipe.egg-info/SOURCES.txt
hgrecipe.egg-info/dependency_links.txt
hgrecipe.egg-info/entry_points.txt
hgrecipe.egg-info/requires.txt
hgrecipe.egg-info/top_level.txt