Metadata-Version: 1.0
Name: hgrecipe
Version: 0.9
Summary: Buildout recipe for cloning sources from a mercurial repository.
Home-page: UNKNOWN
Author: Preston Timmons
Author-email: prestontimmons@gfa.org
License: UNKNOWN
Platform: UNKNOWN
Classifier: Intended Audience :: Developers
Classifier: Programming Language :: Python
Classifier: Topic :: Software Development :: Libraries :: Python Modules
